asclpy/__init__.py
asclpy/cli.py
asclpy/constants.py
asclpy/loader.py
asclpy/midi.py
asclpy/parser.py
asclpy/tuning.py
asclpy/validation.py
asclpy/tunings/Specification - Make your own tuning.ascl
asclpy/tunings/Arabic Maqam/All Maqamat 24EDO.ascl
asclpy/tunings/Arabic Maqam/Bayati 1.ascl
asclpy/tunings/Arabic Maqam/Bayati 2.ascl
asclpy/tunings/Arabic Maqam/Bayati-Saba-Hijaz-Kurd 24EDO.ascl
asclpy/tunings/Arabic Maqam/Bayati-Saba-all.ascl
asclpy/tunings/Arabic Maqam/Hijaz 1.ascl
asclpy/tunings/Arabic Maqam/Hijaz 2.ascl
asclpy/tunings/Arabic Maqam/Hijaz 3.ascl
asclpy/tunings/Arabic Maqam/Hijaz-Bayati-Kurd 24EDO.ascl
asclpy/tunings/Arabic Maqam/Jiharkah.ascl
asclpy/tunings/Arabic Maqam/Rast 1 - Egypt mid 20th.ascl
asclpy/tunings/Arabic Maqam/Rast 2 (Suznak) Egypt Mid 20th.ascl
asclpy/tunings/Arabic Maqam/Rast 24EDO.ascl
asclpy/tunings/Arabic Maqam/Rast 3 - Syrian mid-20th.ascl
asclpy/tunings/Arabic Maqam/Rast 4 - High Ds and As.ascl
asclpy/tunings/Arabic Maqam/Rast 5 - all the modulations.ascl
asclpy/tunings/Arabic Maqam/Rast 6 - modulations + variants.ascl
asclpy/tunings/Arabic Maqam/Rast Family 24EDO.ascl
asclpy/tunings/Arabic Maqam/Saba-Bayati 24EDO.ascl
asclpy/tunings/Arabic Maqam/Saba.ascl
asclpy/tunings/Arabic Maqam/Suznak 24EDO.ascl
asclpy/tunings/EDO/11-EDO.ascl
asclpy/tunings/EDO/12-TET (EDO).ascl
asclpy/tunings/EDO/13-EDO.ascl
asclpy/tunings/EDO/19-EDO.ascl
asclpy/tunings/EDO/22-EDO.ascl
asclpy/tunings/EDO/24-EDO.ascl
asclpy/tunings/EDO/31-EDO.ascl
asclpy/tunings/EDO/35-EDO.ascl
asclpy/tunings/EDO/36-EDO.ascl
asclpy/tunings/EDO/41-EDO.ascl
asclpy/tunings/EDO/43-EDO.ascl
asclpy/tunings/EDO/5-EDO.ascl
asclpy/tunings/EDO/53-EDO.ascl
asclpy/tunings/EDO/55-EDO.ascl
asclpy/tunings/EDO/7-EDO + 5-EDO.ascl
asclpy/tunings/EDO/7-EDO.ascl
asclpy/tunings/EDO/72-EDO.ascl
asclpy/tunings/EDO/Bohlen Pierce.ascl
asclpy/tunings/EDO/Wendy Carlos alpha.ascl
asclpy/tunings/EDO/Wendy Carlos beta.ascl
asclpy/tunings/EDO/Wendy Carlos gamma.ascl
asclpy-0.1.3.dist-info/licenses/LICENSE
asclpy-0.1.3.dist-info/METADATA
asclpy-0.1.3.dist-info/WHEEL
asclpy-0.1.3.dist-info/entry_points.txt
asclpy-0.1.3.dist-info/top_level.txt
asclpy-0.1.3.dist-info/RECORD
