Metadata-Version: 2.4
Name: asclpy
Version: 0.1.3
Summary: Parser for .ascl (Ableton Scala) tuning files with bundled tuning library
Author-email: Brian Abelson <brian@abelson.live>
Project-URL: Homepage, https://github.com/abelsonlive/asclpy
Project-URL: Documentation, https://github.com/abelsonlive/asclpy/blob/main/README.md
Keywords: tuning,ascl,scala,ableton,microtonal,music,midi
Classifier: Development Status :: 4 - Beta
Classifier: Intended Audience :: Developers
Classifier: Topic :: Multimedia :: Sound/Audio
Classifier: Topic :: Software Development :: Libraries :: Python Modules
Classifier: Programming Language :: Python :: 3
Classifier: Programming Language :: Python :: 3.13
Requires-Python: >=3.13
License-File: LICENSE
Requires-Dist: click>=8.0.0
Provides-Extra: dev
Requires-Dist: pytest>=7.0; extra == "dev"
Dynamic: license-file
